mop/__init__.py
mop/snowflake.py
mop/conf/__init__.py
mop/conf/settings.py
mop/crud/__init__.py
mop/crud/crud.py
mop/crud/page.py
mop/db/__init__.py
mop/db/async_session.py
mop/db/base.py
mop/db/session.py
mop/entity/__init__.py
mop/entity/entity.py
mop/error/__init__.py
mop/error/biz_error.py
mop/error/err_code.py
mop/logging/__init__.py
mop/logging/logging.py
mop/response/__init__.py
mop/response/response.py
mop/util/__init__.py
mop/util/dates.py
mop/util/encoder.py
mop/util/files.py
mop/util/strings.py
mop/util/util.py
moss_mop-0.1.0.dist-info/METADATA
moss_mop-0.1.0.dist-info/WHEEL
moss_mop-0.1.0.dist-info/top_level.txt
moss_mop-0.1.0.dist-info/RECORD
