Metadata-Version: 2.4
Name: moss-mop
Version: 0.1.0
Summary: Lightweight FastAPI + SQLAlchemy backend toolkit with logging, CRUD, and utilities
Requires-Python: >=3.12
Requires-Dist: ascii-colors>=0.11.6
Requires-Dist: fastapi>=0.124.4
Requires-Dist: pydantic>=2.12.5
Requires-Dist: sqlalchemy>=2.0.45
Requires-Dist: structlog>=25.5.0
